pscan/__init__.py
pscan-1.0.0.dist-info/DESCRIPTION.rst
pscan-1.0.0.dist-info/METADATA
pscan-1.0.0.dist-info/RECORD
pscan-1.0.0.dist-info/WHEEL
pscan-1.0.0.dist-info/metadata.json
pscan-1.0.0.dist-info/top_level.txt
