Metadata-Version: 2.0
Name: pscan
Version: 1.0.0
Summary: Micro-DSL for specifying parameter scans easily
Home-page: https://github.com/brunobeltran/pscan
Author: Bruno Beltran
Author-email: brunobeltran0@gmail.com
License: MIT
Keywords: parameter scanning scientific search testing
Platform: UNKNOWN
Classifier: Development Status :: 3 - Alpha
Classifier: Intended Audience :: Developers
Classifier: Intended Audience :: Science/Research
Classifier: License :: OSI Approved :: MIT License
Classifier: Topic :: Utilities
